pulser_scaleway/__init__.py
pulser_scaleway/scaleway_service.py
pulser_scaleway/versions.py
pulser_scaleway-0.1.5.dist-info/licenses/LICENSE
pulser_scaleway-0.1.5.dist-info/METADATA
pulser_scaleway-0.1.5.dist-info/WHEEL
pulser_scaleway-0.1.5.dist-info/top_level.txt
pulser_scaleway-0.1.5.dist-info/RECORD
