Metadata-Version: 2.4
Name: pulser_scaleway
Version: 0.1.5
Summary: A Pulser-compatible package to connect to Scaleway Quantum as a Service
Author: The Scaleway Developers
Author-email: vmacheret@scaleway.com
License: Apache 2
Project-URL: Documentation, https://www.scaleway.com/en/quantum-as-a-service/
Project-URL: Source, https://github.com/scaleway/pulser-scaleway
Project-URL: Tracker, https://github.com/scaleway/pulser-scaleway/issues
Requires-Python: >=3.12.0
License-File: LICENSE
Requires-Dist: randomname>=0.2.1
Requires-Dist: scaleway-qaas-client>=0.1.18
Requires-Dist: pulser-core>=1.5.5
Dynamic: author
Dynamic: author-email
Dynamic: description
Dynamic: description-content-type
Dynamic: license
Dynamic: license-file
Dynamic: project-url
Dynamic: requires-dist
Dynamic: requires-python
Dynamic: summary
